README.md
setup.py
ohmm/GetAttributes.py
ohmm/GetData.py
ohmm/Progress.py
ohmm/__init__.py
ohmm/install.py
ohmm/ohmm.py
ohmm/ohmm_studio.py
ohmm.egg-info/PKG-INFO
ohmm.egg-info/SOURCES.txt
ohmm.egg-info/dependency_links.txt
ohmm.egg-info/entry_points.txt
ohmm.egg-info/requires.txt
ohmm.egg-info/top_level.txt